{"uid":"15268429","name":"小鹤aloha","path":"users/15268429/","avatar":"users/15268429/avatar.jpg","avatarURL":"https://i1.hdslb.com/bfs/face/edbe8167d6ea546adfd524c92892d38194379f6b.jpg","videos":[{"bvid":"BV1oKSnBkEYX","title":"「鹤」好想消失／42:7","created":1764381600000,"thumb":"users/15268429/0-thumb.jpg","thumbURL":"http://i1.hdslb.com/bfs/archive/f9b3683f260429afb1525e2cfc411ffee62f2dbd.jpg"},{"bvid":"BV1DgCRBjEZi","title":"「小鹤」星期五的早安","created":1763683200000,"thumb":"users/15268429/1-thumb.jpg","thumbURL":"http://i1.hdslb.com/bfs/archive/09a9e786d72e44274c8958ef55c84cc2ba80c1df.jpg"},{"bvid":"BV1sM2gBDEmL","title":"【各跳各的之这把变态局】少女是心理变态【13人】","created":1763136000000,"thumb":"users/15268429/2-thumb.jpg","thumbURL":"http://i0.hdslb.com/bfs/archive/db949d5fbee060aa6699adc997a700f8539fc932.jpg"}],"updated":true}