{"uid":"34753408","name":"咸猫爱吃鱼","path":"users/34753408/","avatar":"users/34753408/avatar.jpg","avatarURL":"https://i1.hdslb.com/bfs/face/b1df712b607dcd14144c18bc435157bd1d3409c2.jpg","videos":[{"bvid":"BV1HkhxzBEjg","title":"【浮泽舞见四人】LOSER stage ver.【七草祭】","created":1754114400000,"thumb":"users/34753408/0-thumb.jpg","thumbURL":"http://i0.hdslb.com/bfs/archive/a2ed1afa8926c44cb11596eace07951d3fd4fe09.jpg"},{"bvid":"BV1J1hxziEQu","title":"【浮泽舞见4人】LOSER","created":1754114400000,"thumb":"users/34753408/1-thumb.jpg","thumbURL":"http://i1.hdslb.com/bfs/archive/610a900465940faf832c87ddaa55fc7bd2d28cba.jpg"},{"bvid":"BV1sLgJzgEue","title":"【星星×咸猫】Fatal·限定兄妹组合上线！【HB2星星】","created":1753176600000,"thumb":"users/34753408/2-thumb.jpg","thumbURL":"http://i1.hdslb.com/bfs/archive/68cc81cca2fdaab00073521823c373e05f0ed82a.jpg"}],"updated":true}